codeflex/__init__.py
codeflex/company/__init__.py
codeflex/company/mysql.py
codeflex/company/polly.py
codeflex/company/smtp.py
codeflex/mysql/__init__.py
codeflex/mysql/abstracts.py
codeflex/mysql/authentication.py
codeflex/mysql/catch23.py
codeflex/mysql/charsets.py
codeflex/mysql/connection.py
codeflex/mysql/connection_cext.py
codeflex/mysql/constants.py
codeflex/mysql/conversion.py
codeflex/mysql/cursor.py
codeflex/mysql/cursor_cext.py
codeflex/mysql/custom_types.py
codeflex/mysql/dbapi.py
codeflex/mysql/errorcode.py
codeflex/mysql/errors.py
codeflex/mysql/logger.py
codeflex/mysql/network.py
codeflex/mysql/optionfiles.py
codeflex/mysql/pooling.py
codeflex/mysql/protocol.py
codeflex/mysql/py.typed
codeflex/mysql/types.py
codeflex/mysql/utils.py
codeflex/mysql/version.py
codeflex/mysql/aio/__init__.py
codeflex/mysql/aio/abstracts.py
codeflex/mysql/aio/authentication.py
codeflex/mysql/aio/charsets.py
codeflex/mysql/aio/connection.py
codeflex/mysql/aio/cursor.py
codeflex/mysql/aio/logger.py
codeflex/mysql/aio/network.py
codeflex/mysql/aio/protocol.py
codeflex/mysql/aio/utils.py
codeflex/mysql/aio/plugins/__init__.py
codeflex/mysql/aio/plugins/authentication_kerberos_client.py
codeflex/mysql/aio/plugins/authentication_ldap_sasl_client.py
codeflex/mysql/aio/plugins/authentication_oci_client.py
codeflex/mysql/aio/plugins/authentication_webauthn_client.py
codeflex/mysql/aio/plugins/caching_sha2_password.py
codeflex/mysql/aio/plugins/mysql_clear_password.py
codeflex/mysql/aio/plugins/mysql_native_password.py
codeflex/mysql/aio/plugins/sha256_password.py
codeflex/mysql/django/__init__.py
codeflex/mysql/django/base.py
codeflex/mysql/django/client.py
codeflex/mysql/django/compiler.py
codeflex/mysql/django/creation.py
codeflex/mysql/django/features.py
codeflex/mysql/django/introspection.py
codeflex/mysql/django/operations.py
codeflex/mysql/django/schema.py
codeflex/mysql/django/validation.py
codeflex/mysql/fabric/__init__.py
codeflex/mysql/fabric/balancing.py
codeflex-5.1.1.dist-info/LICENSE
codeflex-5.1.1.dist-info/METADATA
codeflex-5.1.1.dist-info/WHEEL
codeflex-5.1.1.dist-info/top_level.txt
codeflex-5.1.1.dist-info/RECORD
