Metadata-Version: 2.2
Name: codeflex
Version: 5.1.1
Summary: ¡Conecta a los Microservicios de CodeFlex desde una Sola Librería!
Home-page: https://codeflex.com.co/
Author: CODEFLEX S.A.S.
Author-email: info@codeflex.com.co
License: This software is owned by CodeFlex S.A.S. and is protected by applicable copyright laws. The distribution and use of this software are subject to the terms and conditions outlined below.
Project-URL: Bug Tracker, https://docs.codeflex.com.co/
Classifier: Programming Language :: Python :: 3
Classifier: License :: OSI Approved :: MIT License
Classifier: Operating System :: OS Independent
Requires-Python: >=3.6
License-File: LICENSE
Requires-Dist: idna
Requires-Dist: charset_normalizer
Requires-Dist: chardet
Requires-Dist: urllib3
Requires-Dist: certifi
Requires-Dist: werkzeug
Requires-Dist: click
Requires-Dist: blinker
Requires-Dist: jinja2
Requires-Dist: Flask
Requires-Dist: itsdangerous
Dynamic: author
Dynamic: author-email
Dynamic: classifier
Dynamic: description
Dynamic: description-content-type
Dynamic: home-page
Dynamic: license
Dynamic: project-url
Dynamic: requires-dist
Dynamic: requires-python
Dynamic: summary
